Neuron/__init__.py
Neuron/perceptron.py
oneNeuron_sairam852-0.0.2.dist-info/LICENSE
oneNeuron_sairam852-0.0.2.dist-info/METADATA
oneNeuron_sairam852-0.0.2.dist-info/WHEEL
oneNeuron_sairam852-0.0.2.dist-info/top_level.txt
oneNeuron_sairam852-0.0.2.dist-info/RECORD
