Metadata-Version: 2.1
Name: oneNeuron-sairam852
Version: 0.0.2
Summary: it is an implimentation of perceptron
Home-page: https://github.com/sairam852/oneNeuron
Author: sairam852
Author-email: racsai574@gmail.com
License: UNKNOWN
Project-URL: Bug Tracker, https://github.com/{USER_NAME}/{PROJECT_NAME}/issues
Platform: UNKNOWN
Classifier: Programming Language :: Python :: 3
Classifier: License :: OSI Approved :: MIT License
Classifier: Operating System :: OS Independent
Requires-Python: >=3.6
License-File: LICENSE
Requires-Dist: numpy
Requires-Dist: tqdm
